{
  "GV001" : {
    "Orden" : {
      "EGV2363" : {
        "Apellidos_Estudiante" : "Orejuela Salazar",
        "Curso" : "décimo-d",
        "Nombres_Estudiante" : "Zharick"
      },
      "EGV2495" : {
        "Apellidos_Estudiante" : "Bermeo Barahona",
        "Curso" : "octavo-d",
        "Nombres_Estudiante" : "Lucia"
      },
      "EGV2526" : {
        "Apellidos_Estudiante" : "Bermeo Barahona",
        "Curso" : "séptimo-d",
        "Nombres_Estudiante" : "Alejandra"
      },
      "EGV6401" : {
        "Apellidos_Estudiante" : "Sanchez Figueroa",
        "Curso" : "séptimo-f",
        "Nombres_Estudiante" : "Mariana"
      },
      "EGV6863" : {
        "Apellidos_Estudiante" : "Pinzon Popayan",
        "Curso" : "primero-f",
        "Nombres_Estudiante" : "Maria Jose"
      },
      "EGV6927" : {
        "Apellidos_Estudiante" : "Castañeda Ramos",
        "Curso" : "transición-g",
        "Nombres_Estudiante" : "Maria Jose"
      },
      "EGV7063" : {
        "Apellidos_Estudiante" : "Briñez Gonzalez",
        "Curso" : "primero-f",
        "Nombres_Estudiante" : "Sarai"
      },
      "EGV7076" : {
        "Apellidos_Estudiante" : "Rosas Lopez",
        "Curso" : "transición-g",
        "Nombres_Estudiante" : "Maria Camila"
      },
      "EGV8185" : {
        "Apellidos_Estudiante" : "Garcia Ospina",
        "Curso" : "séptimo-a",
        "Nombres_Estudiante" : "Daniel"
      },
      "EGV8523" : {
        "Apellidos_Estudiante" : "Guevara Sanchez",
        "Curso" : "tercero-c",
        "Nombres_Estudiante" : "Samuel"
      },
      "EGV8641" : {
        "Apellidos_Estudiante" : "Palacio Gamez",
        "Curso" : "segundo-c",
        "Nombres_Estudiante" : "Gabriel"
      },
      "EGV8823" : {
        "Apellidos_Estudiante" : "Guevara Sanchez",
        "Curso" : "transición-a",
        "Nombres_Estudiante" : "Jeronimo"
      },
      "EGV8841" : {
        "Apellidos_Estudiante" : "Poveda Torres",
        "Curso" : "transición-b",
        "Nombres_Estudiante" : "Juan Pablo"
      },
      "EGV8999" : {
        "Apellidos_Estudiante" : "Rebellón León",
        "Curso" : "kinder-g",
        "Nombres_Estudiante" : "Isabella"
      },
      "EGV9037" : {
        "Apellidos_Estudiante" : "Hung Guio",
        "Curso" : "prekinder-d",
        "Nombres_Estudiante" : "Avril"
      },
      "EGV9099" : {
        "Apellidos_Estudiante" : "Briñez Gonzalez",
        "Curso" : "prekinder-d",
        "Nombres_Estudiante" : "Luciana"
      },
      "EGV9109" : {
        "Apellidos_Estudiante" : "Amaya Rodriguez",
        "Curso" : "prekinder-d",
        "Nombres_Estudiante" : "Luciana"
      }
    }
  },
  "GV002" : {
    "Orden" : {
      "EGV2230" : {
        "Apellidos_Estudiante" : "Rincon Rodriguez",
        "Curso" : "décimo-e",
        "Nombres_Estudiante" : "Maria Paula"
      },
      "EGV2355" : {
        "Apellidos_Estudiante" : "Angel Mora",
        "Curso" : "octavo-e",
        "Nombres_Estudiante" : "Laura Sofia"
      },
      "EGV2372" : {
        "Apellidos_Estudiante" : "Gutierrez Carrillo",
        "Curso" : "noveno-e",
        "Nombres_Estudiante" : "Tatiana Lucia"
      },
      "EGV2515" : {
        "Apellidos_Estudiante" : "Montaña Fandiño",
        "Curso" : "noveno-f",
        "Nombres_Estudiante" : "Maria Paula"
      },
      "EGV6586" : {
        "Apellidos_Estudiante" : "Sanchez Valencia",
        "Curso" : "cuarto-d",
        "Nombres_Estudiante" : "Antonia"
      },
      "EGV6646" : {
        "Apellidos_Estudiante" : "Gutierrez Gonzalez",
        "Curso" : "tercero-f",
        "Nombres_Estudiante" : "Elena"
      },
      "EGV6797" : {
        "Apellidos_Estudiante" : "Wiesner Restrepo",
        "Curso" : "segundo-f",
        "Nombres_Estudiante" : "Mariana"
      },
      "EGV6890" : {
        "Apellidos_Estudiante" : "Aparicio Mendoza",
        "Curso" : "cuarto-e",
        "Nombres_Estudiante" : "Isabella"
      },
      "EGV6898" : {
        "Apellidos_Estudiante" : "Aparicio Mendoza",
        "Curso" : "primero-e",
        "Nombres_Estudiante" : "Maria Alejandra"
      },
      "EGV706" : {
        "Apellidos_Estudiante" : "Angel Mora",
        "Curso" : "undécimo-a",
        "Nombres_Estudiante" : "Andres Mauricio"
      },
      "EGV7127" : {
        "Apellidos_Estudiante" : "Salazar Amaya",
        "Curso" : "kinder-g",
        "Nombres_Estudiante" : "Lucia"
      },
      "EGV7766" : {
        "Apellidos_Estudiante" : "Palacios Herran",
        "Curso" : "undécimo-a",
        "Nombres_Estudiante" : "Jose Miguel"
      },
      "EGV7836" : {
        "Apellidos_Estudiante" : "Cardenas Ortiz",
        "Curso" : "undécimo-a",
        "Nombres_Estudiante" : "Juan David"
      },
      "EGV7930" : {
        "Apellidos_Estudiante" : "Palacios Herran",
        "Curso" : "noveno-c",
        "Nombres_Estudiante" : "Juan Angel"
      },
      "EGV8071" : {
        "Apellidos_Estudiante" : "Calderon Rodriguez",
        "Curso" : "noveno-b",
        "Nombres_Estudiante" : "Hector Daniel"
      },
      "EGV8174" : {
        "Apellidos_Estudiante" : "Maestre Botello",
        "Curso" : "octavo-a",
        "Nombres_Estudiante" : "Jose Miguel"
      },
      "EGV8547" : {
        "Apellidos_Estudiante" : "Salazar Ternera",
        "Curso" : "tercero-a",
        "Nombres_Estudiante" : "Juan Felipe"
      },
      "EGV8666" : {
        "Apellidos_Estudiante" : "Vasquez Sabogal",
        "Curso" : "segundo-c",
        "Nombres_Estudiante" : "Felipe"
      },
      "EGV8745" : {
        "Apellidos_Estudiante" : "Salazar Amaya",
        "Curso" : "primero-c",
        "Nombres_Estudiante" : "Juan Jose"
      },
      "EGV8760" : {
        "Apellidos_Estudiante" : "Gomez Lopez",
        "Curso" : "primero-b",
        "Nombres_Estudiante" : "Martin"
      },
      "EGV8915" : {
        "Apellidos_Estudiante" : "García Aja",
        "Curso" : "kinder-a",
        "Nombres_Estudiante" : "Martín"
      },
      "EGV8981" : {
        "Apellidos_Estudiante" : "Niño Dussan",
        "Curso" : "kinder-b",
        "Nombres_Estudiante" : "Jeronimo"
      },
      "EGV9003" : {
        "Apellidos_Estudiante" : "Agudelo Castro",
        "Curso" : "kinder-b",
        "Nombres_Estudiante" : "Alejandro"
      },
      "EGV9082" : {
        "Apellidos_Estudiante" : "Burbano Rodriguez",
        "Curso" : "prekinder-c",
        "Nombres_Estudiante" : "Sofia"
      },
      "EGV9085" : {
        "Apellidos_Estudiante" : "Wiesner Restrepo",
        "Curso" : "prekinder-c",
        "Nombres_Estudiante" : "Catalina"
      }
    }
  },
  "GV003" : {
    "Orden" : {
      "EGV2563" : {
        "Apellidos_Estudiante" : "Morales Martinez",
        "Curso" : "séptimo-e",
        "Nombres_Estudiante" : "Juanita"
      },
      "EGV6330" : {
        "Apellidos_Estudiante" : "Cobo Ruiz",
        "Curso" : "sexto-e",
        "Nombres_Estudiante" : "Isabel Sofia"
      },
      "EGV6777" : {
        "Apellidos_Estudiante" : "Peña Portilla",
        "Curso" : "segundo-d",
        "Nombres_Estudiante" : "Antonia"
      },
      "EGV6858" : {
        "Apellidos_Estudiante" : "Parra Lezama",
        "Curso" : "primero-e",
        "Nombres_Estudiante" : "Camila"
      },
      "EGV6916" : {
        "Apellidos_Estudiante" : "Alvarez Ramirez",
        "Curso" : "transición-g",
        "Nombres_Estudiante" : "Ivanna"
      },
      "EGV6942" : {
        "Apellidos_Estudiante" : "Gaitan Arguello",
        "Curso" : "transición-f",
        "Nombres_Estudiante" : "Gabriela"
      },
      "EGV6978" : {
        "Apellidos_Estudiante" : "Ropero Santamaria",
        "Curso" : "transición-f",
        "Nombres_Estudiante" : "Gabriela"
      },
      "EGV6983" : {
        "Apellidos_Estudiante" : "Velandia Castro",
        "Curso" : "transición-g",
        "Nombres_Estudiante" : "Alicia"
      },
      "EGV7149" : {
        "Apellidos_Estudiante" : "Diez Montes",
        "Curso" : "kinder-d",
        "Nombres_Estudiante" : "Sofia"
      },
      "EGV7887" : {
        "Apellidos_Estudiante" : "Gonzalez Sanchez",
        "Curso" : "noveno-b",
        "Nombres_Estudiante" : "Samuel Alejandro"
      },
      "EGV7932" : {
        "Apellidos_Estudiante" : "Maria Valderrama",
        "Curso" : "noveno-b",
        "Nombres_Estudiante" : "Sebastian"
      },
      "EGV8010" : {
        "Apellidos_Estudiante" : "Homez Delgado",
        "Curso" : "octavo-b",
        "Nombres_Estudiante" : "Santiago"
      },
      "EGV8100" : {
        "Apellidos_Estudiante" : "Amado Segura",
        "Curso" : "séptimo-c",
        "Nombres_Estudiante" : "Juan Camilo"
      },
      "EGV8129" : {
        "Apellidos_Estudiante" : "Molano Cornejo",
        "Curso" : "séptimo-a",
        "Nombres_Estudiante" : "Juan Felipe"
      },
      "EGV8187" : {
        "Apellidos_Estudiante" : "Rico Riveros",
        "Curso" : "séptimo-b",
        "Nombres_Estudiante" : "Martin"
      },
      "EGV8364" : {
        "Apellidos_Estudiante" : "Laverde Cardona",
        "Curso" : "quinto-b",
        "Nombres_Estudiante" : "David"
      },
      "EGV8460" : {
        "Apellidos_Estudiante" : "Viasus Perez",
        "Curso" : "cuarto-a",
        "Nombres_Estudiante" : "Samuel"
      },
      "EGV8493" : {
        "Apellidos_Estudiante" : "Laverde Cardona",
        "Curso" : "tercero-b",
        "Nombres_Estudiante" : "Felipe"
      },
      "EGV8765" : {
        "Apellidos_Estudiante" : "Garzon Vergara",
        "Curso" : "primero-c",
        "Nombres_Estudiante" : "Efrain"
      },
      "EGV8812" : {
        "Apellidos_Estudiante" : "Cobo Ruiz",
        "Curso" : "transición-b",
        "Nombres_Estudiante" : "David Alejandro"
      },
      "EGV8881" : {
        "Apellidos_Estudiante" : "Parra Lezama",
        "Curso" : "transición-b",
        "Nombres_Estudiante" : "Andres"
      },
      "EGV9071" : {
        "Apellidos_Estudiante" : "Niño Amaya",
        "Curso" : "prekinder-b",
        "Nombres_Estudiante" : "Juan"
      },
      "EGV9088" : {
        "Apellidos_Estudiante" : "Gaitán Arguello",
        "Curso" : "prekinder-b",
        "Nombres_Estudiante" : "Gerónimo"
      }
    }
  },
  "GV004" : {
    "Orden" : {
      "EGV2169" : {
        "Apellidos_Estudiante" : "Lombana Fino",
        "Curso" : "undécimo-d",
        "Nombres_Estudiante" : "Sofia"
      },
      "EGV2189" : {
        "Apellidos_Estudiante" : "Martinez Camino",
        "Curso" : "undécimo-c",
        "Nombres_Estudiante" : "Laura Sofia"
      },
      "EGV2192" : {
        "Apellidos_Estudiante" : "Salazar Zambrano",
        "Curso" : "undécimo-d",
        "Nombres_Estudiante" : "Maria Monica"
      },
      "EGV2303" : {
        "Apellidos_Estudiante" : "Barajas Gomez",
        "Curso" : "noveno-e",
        "Nombres_Estudiante" : "Andrea Catalina"
      },
      "EGV2437" : {
        "Apellidos_Estudiante" : "Garzon Melendez",
        "Curso" : "octavo-d",
        "Nombres_Estudiante" : "Ana Maria"
      },
      "EGV2444" : {
        "Apellidos_Estudiante" : "Lombana Fino",
        "Curso" : "octavo-e",
        "Nombres_Estudiante" : "Isabella"
      },
      "EGV2596" : {
        "Apellidos_Estudiante" : "Verdugo Barragan",
        "Curso" : "séptimo-f",
        "Nombres_Estudiante" : "Mariana"
      },
      "EGV6359" : {
        "Apellidos_Estudiante" : "Paz Barreto",
        "Curso" : "sexto-e",
        "Nombres_Estudiante" : "Sofia"
      },
      "EGV6602" : {
        "Apellidos_Estudiante" : "Zambrano Idarraga",
        "Curso" : "cuarto-e",
        "Nombres_Estudiante" : "Valerie"
      },
      "EGV6638" : {
        "Apellidos_Estudiante" : "Ocampo Martin",
        "Curso" : "tercero-f",
        "Nombres_Estudiante" : "Juanita"
      },
      "EGV6689" : {
        "Apellidos_Estudiante" : "Zapata Lagos",
        "Curso" : "tercero-d",
        "Nombres_Estudiante" : "Amelia"
      },
      "EGV6699" : {
        "Apellidos_Estudiante" : "Giraldo Gomez",
        "Curso" : "tercero-f",
        "Nombres_Estudiante" : "Luciana"
      },
      "EGV6811" : {
        "Apellidos_Estudiante" : "Alvarez Ramos",
        "Curso" : "tercero-e",
        "Nombres_Estudiante" : "Valentina Maria"
      },
      "EGV6889" : {
        "Apellidos_Estudiante" : "Cortes Rivera",
        "Curso" : "primero-e",
        "Nombres_Estudiante" : "María José"
      },
      "EGV6920" : {
        "Apellidos_Estudiante" : "Avendaño Hernandez",
        "Curso" : "transición-e",
        "Nombres_Estudiante" : "Ana Mia"
      },
      "EGV6974" : {
        "Apellidos_Estudiante" : "Quiroga Posada",
        "Curso" : "transición-f",
        "Nombres_Estudiante" : "Isabella"
      },
      "EGV7059" : {
        "Apellidos_Estudiante" : "Mariño Triviño",
        "Curso" : "transición-g",
        "Nombres_Estudiante" : "Sara"
      },
      "EGV7104" : {
        "Apellidos_Estudiante" : "Mariño Triviño",
        "Curso" : "kinder-e",
        "Nombres_Estudiante" : "Valeria"
      },
      "EGV7913" : {
        "Apellidos_Estudiante" : "Perez Valbuena",
        "Curso" : "noveno-c",
        "Nombres_Estudiante" : "Juan David"
      },
      "EGV8120" : {
        "Apellidos_Estudiante" : "Gutierrez Chadid",
        "Curso" : "séptimo-c",
        "Nombres_Estudiante" : "Mateo"
      },
      "EGV8203" : {
        "Apellidos_Estudiante" : "Ciendua Salamanca",
        "Curso" : "sexto-b",
        "Nombres_Estudiante" : "Samuel"
      },
      "EGV8252" : {
        "Apellidos_Estudiante" : "Vargas Barrera",
        "Curso" : "sexto-b",
        "Nombres_Estudiante" : "Juan Daniel"
      },
      "EGV8275" : {
        "Apellidos_Estudiante" : "Murcia Sanchez",
        "Curso" : "sexto-c",
        "Nombres_Estudiante" : "Santiago"
      },
      "EGV8374" : {
        "Apellidos_Estudiante" : "Ordoñez Barrera",
        "Curso" : "quinto-a",
        "Nombres_Estudiante" : "Juan Pablo"
      },
      "EGV8425" : {
        "Apellidos_Estudiante" : "Ocampo Martin",
        "Curso" : "cuarto-a",
        "Nombres_Estudiante" : "Juan Miguel"
      },
      "EGV8459" : {
        "Apellidos_Estudiante" : "Vargas Manosalva",
        "Curso" : "cuarto-c",
        "Nombres_Estudiante" : "Emmanuel"
      },
      "EGV8587" : {
        "Apellidos_Estudiante" : "Alzate Chadid",
        "Curso" : "segundo-b",
        "Nombres_Estudiante" : "Juan David"
      },
      "EGV8917" : {
        "Apellidos_Estudiante" : "Giraldo Gomez",
        "Curso" : "kinder-a",
        "Nombres_Estudiante" : "Maximiliano"
      },
      "EGV9083" : {
        "Apellidos_Estudiante" : "Giraldo Gomez",
        "Curso" : "prekinder-d",
        "Nombres_Estudiante" : "Guadalupe"
      },
      "EGV9106" : {
        "Apellidos_Estudiante" : "Puerta Hincapie",
        "Curso" : "prekinder-c",
        "Nombres_Estudiante" : "Antonia"
      }
    }
  }
}
